chdimage-0.2.1.dist-info/METADATA
chdimage-0.2.1.dist-info/WHEEL
chdimage-0.2.1.dist-info/license_files/LICENSE
chdimage/__init__.py
chdimage/chdimage.abi3.so
chdimage-0.2.1.dist-info/RECORD
