Metadata-Version: 2.1
Name: chdimage
Version: 0.2.1
Classifier: Programming Language :: Rust
Classifier: Operating System :: POSIX :: Linux
Classifier: Operating System :: Microsoft :: Windows
Classifier: Operating System :: MacOS :: MacOS X
License-File: LICENSE
Summary: Python bindings to the chdimage part of https://github.com/Manorhos/imageparse
Keywords: chd,cd,parser,decompression,delta encoding,checksum
Requires-Python: >=3.8
Project-URL: repository, https://github.com/i30817/chdimage
